README.md
setup.py
langchain_bailian/__init__.py
langchain_bailian/bailian_llm.py
langchain_bailian.egg-info/PKG-INFO
langchain_bailian.egg-info/SOURCES.txt
langchain_bailian.egg-info/dependency_links.txt
langchain_bailian.egg-info/requires.txt
langchain_bailian.egg-info/top_level.txt